[{"line":2,"elements":[{"start_timestamp":"2024-05-17T08:23:45.055Z","line":15,"name":"Quote request by giving all necessary inputs","description":"","id":"get-a-quote-successful-submission;quote-request-by-giving-all-necessary-inputs;;2","after":[{"result":{"duration":257886300,"status":"passed"},"match":{"location":"hooks.Hooks.teardown()"}}],"type":"scenario","keyword":"Scenario Outline","steps":[{"result":{"duration":4481488200,"status":"passed"},"line":7,"name":"I am quote generator using \"chrome\" for valid details","match":{"arguments":[{"val":"\"chrome\"","offset":27}],"location":"StepDefinition.GetQuote.quote_genrator_leagal_inputs(java.lang.String)"},"keyword":"Given "},{"result":{"duration":1114933100,"status":"passed"},"line":8,"name":"I enter valid Text box details","match":{"location":"StepDefinition.GetQuote.user_enter_valid_job_details()"},"keyword":"When "},{"result":{"duration":161712200,"status":"passed"},"line":9,"name":"I enter Country details","match":{"location":"StepDefinition.GetQuote.Enter_Country()"},"keyword":"And "},{"result":{"duration":656328700,"status":"passed"},"line":10,"name":"I look for Related Documents","match":{"location":"StepDefinition.GetQuote.Related_Documents()"},"keyword":"And "},{"result":{"duration":284992800,"status":"passed"},"line":11,"name":"Provided the additional info and accepted the privacy policy","match":{"location":"StepDefinition.GetQuote.All_Remaining_Info()"},"keyword":"And "},{"result":{"duration":46230200,"status":"passed"},"line":12,"name":"I could see my quote was submitted successfully","match":{"location":"StepDefinition.GetQuote.Submit_Quote()"},"keyword":"Then "}],"tags":[{"name":"@skryabin"}]},{"start_timestamp":"2024-05-17T08:23:52.107Z","line":16,"name":"Quote request by giving all necessary inputs","description":"","id":"get-a-quote-successful-submission;quote-request-by-giving-all-necessary-inputs;;3","after":[{"result":{"duration":351809800,"status":"passed"},"match":{"location":"hooks.Hooks.teardown()"}}],"type":"scenario","keyword":"Scenario Outline","steps":[{"result":{"duration":9907998700,"status":"passed"},"line":7,"name":"I am quote generator using \"edge\" for valid details","match":{"arguments":[{"val":"\"edge\"","offset":27}],"location":"StepDefinition.GetQuote.quote_genrator_leagal_inputs(java.lang.String)"},"keyword":"Given "},{"result":{"duration":1269048000,"status":"passed"},"line":8,"name":"I enter valid Text box details","match":{"location":"StepDefinition.GetQuote.user_enter_valid_job_details()"},"keyword":"When "},{"result":{"duration":109874700,"status":"passed"},"line":9,"name":"I enter Country details","match":{"location":"StepDefinition.GetQuote.Enter_Country()"},"keyword":"And "},{"result":{"duration":3018070300,"status":"passed"},"line":10,"name":"I look for Related Documents","match":{"location":"StepDefinition.GetQuote.Related_Documents()"},"keyword":"And "},{"result":{"duration":540436700,"status":"passed"},"line":11,"name":"Provided the additional info and accepted the privacy policy","match":{"location":"StepDefinition.GetQuote.All_Remaining_Info()"},"keyword":"And "},{"result":{"duration":74968700,"status":"passed"},"line":12,"name":"I could see my quote was submitted successfully","match":{"location":"StepDefinition.GetQuote.Submit_Quote()"},"keyword":"Then "}],"tags":[{"name":"@skryabin"}]}],"name":"Get a quote successful submission","description":"  As a quote requestor\n  I want to generate a successful quote","id":"get-a-quote-successful-submission","keyword":"Feature","uri":"file:src/test/java/features/skryabin.feature","tags":[{"name":"@skryabin","type":"Tag","location":{"line":1,"column":1}}]}]